agb_sdk/__main__.py
agb_sdk/__version__.py
agb_sdk/core/__init__.py
agb_sdk/core/dtos/__init__.py
agb_sdk/core/dtos/analysis.py
agb_sdk/core/dtos/biotax_response.py
agb_sdk/core/dtos/biotrop_bioindex.py
agb_sdk/core/dtos/ggh_dimension.py
agb_sdk/core/dtos/locale.py
agb_sdk/core/dtos/mixin.py
agb_sdk/core/entities/__init__.py
agb_sdk/core/entities/analysis.py
agb_sdk/core/exceptions/__init__.py
agb_sdk/core/use_cases/__init__.py
agb_sdk/core/use_cases/convert_bioindex_to_tabular.py
agb_sdk/core/use_cases/get_bioindex_by_id.py
agb_sdk/core/use_cases/list_analysis.py
agb_sdk/ports/__init__.py
agb_sdk/ports/cli/__init__.py
agb_sdk/ports/cli/main.py
agb_sdk/service/__init__.py
agb_sdk/service/analysis.py
agb_sdk/settings.py
tests/__init__.py
tests/mock/customer-record.jsonc
tests/mock/expected-bioidnex-data.jsonc
tests/test_dtos.py
tests/test_use_cases.py
agrobiota_sdk-0.1.0a10.dist-info/METADATA
agrobiota_sdk-0.1.0a10.dist-info/WHEEL
agrobiota_sdk-0.1.0a10.dist-info/entry_points.txt
agrobiota_sdk-0.1.0a10.dist-info/RECORD
